hakushin/__init__.py
hakushin/client.py
hakushin/clients/__init__.py
hakushin/clients/base.py
hakushin/clients/gi.py
hakushin/clients/hsr.py
hakushin/clients/zzz.py
hakushin/constants.py
hakushin/enums.py
hakushin/errors.py
hakushin/models/__init__.py
hakushin/models/base.py
hakushin/models/gi/__init__.py
hakushin/models/gi/artifact.py
hakushin/models/gi/character.py
hakushin/models/gi/mw.py
hakushin/models/gi/new.py
hakushin/models/gi/stygian.py
hakushin/models/gi/weapon.py
hakushin/models/hsr/__init__.py
hakushin/models/hsr/character.py
hakushin/models/hsr/endgame.py
hakushin/models/hsr/enemy_groups.py
hakushin/models/hsr/light_cone.py
hakushin/models/hsr/monster.py
hakushin/models/hsr/new.py
hakushin/models/hsr/relic.py
hakushin/models/zzz/__init__.py
hakushin/models/zzz/bangboo.py
hakushin/models/zzz/character.py
hakushin/models/zzz/common.py
hakushin/models/zzz/disc.py
hakushin/models/zzz/items.py
hakushin/models/zzz/new.py
hakushin/models/zzz/weapon.py
hakushin/utils.py
hakushin_py-0.5.2.dist-info/WHEEL
hakushin_py-0.5.2.dist-info/METADATA
hakushin_py-0.5.2.dist-info/RECORD
