Metadata-Version: 2.3
Name: hakushin-py
Version: 0.5.2
Summary: Async API wrapper for hakush.in written in Python
Author: seriaati
Author-email: seriaati <seria.ati@gmail.com>
License: GNU GENERAL PUBLIC LICENSE
Requires-Dist: aiohttp-client-cache[sqlite]>=0.12.3
Requires-Dist: aiohttp>=3.10.9
Requires-Dist: loguru>=0.7.2
Requires-Dist: pydantic>=2.9.2
Requires-Python: >=3.11
Project-URL: Homepage, https://github.com/seriaati/hakushin-py
Project-URL: Issues, https://github.com/seriaati/hakushin-py/issues
Project-URL: Repository, https://github.com/seriaati/hakushin-py.git
